CONTRIBUTING.rst
HISTORY.rst
LICENSE
MANIFEST.in
README.rst
setup.cfg
setup.py
docs/Makefile
docs/conf.py
docs/contributing.rst
docs/history.rst
docs/index.rst
docs/installation.rst
docs/make.bat
docs/readme.rst
docs/usage.rst
lazysecrets/__init__.py
lazysecrets/main.py
lazysecrets.egg-info/PKG-INFO
lazysecrets.egg-info/SOURCES.txt
lazysecrets.egg-info/dependency_links.txt
lazysecrets.egg-info/not-zip-safe
lazysecrets.egg-info/top_level.txt
tests/__init__.py
tests/test_lazysecrets.py