Metadata-Version: 1.1
Name: lazysecrets
Version: 0.3.0
Summary: Short description here
Home-page: https://github.com/rev112/lazysecrets
Author: Anton Ovchinnikov
Author-email: anton.ovchi2nikov@gmail.com
License: MIT license
Keywords: lazysecrets
Platform: UNKNOWN
Classifier: Development Status :: 2 - Pre-Alpha
Classifier: Intended Audience :: Developers
Classifier: License :: OSI Approved :: MIT License
Classifier: Natural Language :: English
Classifier: Programming Language :: Python :: 2
Classifier: Programming Language :: Python :: 2.6
Classifier: Programming Language :: Python :: 2.7
Classifier: Programming Language :: Python :: 3
Classifier: Programming Language :: Python :: 3.3
Classifier: Programming Language :: Python :: 3.4
Classifier: Programming Language :: Python :: 3.5
